astrodbkit2/__init__.py
astrodbkit2/astrodb.py
astrodbkit2/schema_example.py
astrodbkit2/spectra.py
astrodbkit2/utils.py
astrodbkit2/version.py
astrodbkit2/views.py
astrodbkit2/tests/__init__.py
astrodbkit2/tests/test_astrodb.py
astrodbkit2/tests/test_spectra.py
astrodbkit2/tests/test_utils.py
astrodbkit2/tests/test_views.py
astrodbkit2-0.6.0.dist-info/METADATA
astrodbkit2-0.6.0.dist-info/WHEEL
astrodbkit2-0.6.0.dist-info/top_level.txt
astrodbkit2-0.6.0.dist-info/RECORD
