Metadata-Version: 2.1
Name: astrodbkit2
Version: 0.6.0
Summary: Astronomical database handler code
Author: David Rodriguez
Author-email: David Rodriguez <drodriguez@stsci.edu>
License: BSD 3-Clause
Project-URL: Repository, https://github.com/astrodbtoolkit/AstrodbKit2
Requires-Python: >=3.7
Requires-Dist: astropy
Requires-Dist: astroquery
Requires-Dist: sqlalchemy >=2.0
Requires-Dist: pandas >=1.0.4
Requires-Dist: packaging
Requires-Dist: specutils >=1.0
Requires-Dist: tqdm
Provides-Extra: all
Requires-Dist: astrodbkit2[docs,test] ; extra == 'all'
Provides-Extra: docs
Requires-Dist: sphinx-astropy ; extra == 'docs'
Provides-Extra: test
Requires-Dist: pytest ; extra == 'test'
Requires-Dist: pytest-cov ; extra == 'test'
Requires-Dist: pytest-astropy ; extra == 'test'
Requires-Dist: darker ==1.7.2 ; extra == 'test'
Requires-Dist: black ==23.9.1 ; extra == 'test'
Requires-Dist: pre-commit ==3.4.0 ; extra == 'test'
Requires-Dist: ruff ==0.3.7 ; extra == 'test'
